deepacstrain/__init__.py
deepacstrain/command_line.py
deepacstrain/builtin/config/nn-patric-strain-rapid-sensitive-cnn.ini
deepacstrain/builtin/weights/nn-patric-strain-rapid-sensitive-cnn.h5
deepacstrain-0.2.1.dist-info/LICENSE
deepacstrain-0.2.1.dist-info/METADATA
deepacstrain-0.2.1.dist-info/WHEEL
deepacstrain-0.2.1.dist-info/entry_points.txt
deepacstrain-0.2.1.dist-info/top_level.txt
deepacstrain-0.2.1.dist-info/RECORD
