Metadata-Version: 2.1
Name: deepacstrain
Version: 0.2.1
Summary: Predicting pathogenic potentials of novel strains of known bacterial species.
Home-page: https://gitlab.com/rki_bioinformatics/DeePaC
Author: Jakub Bartoszewicz
Author-email: jakub.bartoszewicz@hpi.de
License: MIT
Keywords: deep learning DNA sequencing synthetic biology pathogenicity prediction
Platform: UNKNOWN
Classifier: Development Status :: 4 - Beta
Classifier: License :: OSI Approved :: MIT License
Classifier: Programming Language :: Python :: 3
Classifier: Programming Language :: Python :: 3.6
Classifier: Topic :: Scientific/Engineering :: Bio-Informatics
Requires-Python: >=3
Requires-Dist: deepac (>=0.11.0)
Requires-Dist: tensorflow (>=2.1)
Requires-Dist: scikit-learn (>=0.22.1)
Requires-Dist: numpy (>=1.17)
Requires-Dist: matplotlib (>=3.1.3)
